LICENSE
MANIFEST.in
README.org
requirements.txt
setup.py
./__init__.py
./default.py
./default_test.py
./scaled.py
./scaled_test.py
./version.py
threading_sched.egg-info/PKG-INFO
threading_sched.egg-info/SOURCES.txt
threading_sched.egg-info/dependency_links.txt
threading_sched.egg-info/top_level.txt