Metadata-Version: 1.1
Name: threading-sched
Version: 1.0.0
Summary: Threading_sched implements a Thread-safe version of Python sched
Home-page: https://github.com/pjkundert/threading_sched
Author: Perry Kundert
Author-email: perry@hardconsulting.com
License: GPLv3
Keywords: sched Thread
Platform: UNKNOWN
Classifier: License :: OSI Approved :: GNU General Public License v3 or later (GPLv3+)
Classifier: Programming Language :: Python :: 2.6
Classifier: Programming Language :: Python :: 2.7
Classifier: Programming Language :: Python :: 3.3
Classifier: Programming Language :: Python :: 3.4
Classifier: Programming Language :: Python :: 3.5
Classifier: Development Status :: 5 - Production/Stable
Classifier: Intended Audience :: Developers
Classifier: Environment :: Console
Classifier: Topic :: Software Development :: Libraries :: Python Modules
